{
	"configurationSettings": [{
		"category": "General Settings",
		"fields": [{
			"type": "webmap"
		},
		{
			"type": "options",
			"fieldName": "language",
			"tooltip": "Should be the language of the title/subtitle provided",
			"label": "Choose a default language:",
			"options": [{
				"value": "en",
				"label": "English"
			},
			{
				"value": "fr",
				"label": "French"
			},
			{
				"value": "es",
				"label": "Spanish"
			},
			{
				"value": "id",
				"label": "Indonesian"
			},
			{
				"value": "zh",
				"label": "Chinese"
      },
			{
				"value": "ka",
				"label": "Georgian"
      }]
		},
		{
			"type": "string",
			"fieldName": "title",
			"label": "Title for your application",
			"tooltip": "Please enter the title in your default language",
			"placeholder": "e.g. Forest Atlas of ..."
		},
		{
			"type": "string",
			"fieldName": "subtitle",
			"label": "Subtitle for your application",
			"tooltip": "Please enter the subtitle in your default language",
			"placeholder": "e.g. My Organisation"
		},
		{
			"type": "string",
			"stringFieldOption": "richtext",
			"fieldName": "narrative",
			"label": "Enter a narrative about your map to give your users some insight about it.",
			"tooltip": "This will be visible in the table of contents.",
			"placeholder": "Explore this map to discover ..."
		},
		{
			"type": "string",
			"fieldName": "webmapMenuName",
			"label": "Title for the menu of your webmap",
			"tooltip": "Menu title configured in your main language.",
			"placeholder": "Land Use"
		},
		{
			"type": "string",
			"fieldName": "logoUrl",
			"label": "Enter the url to your application logo (image should have equal height and width between 60px and 240px)",
			"tooltip": "Make sure this is a publicly available url",
			"placeholder": "e.g. https://www.company.com/logo.png"
		},
		{
			"type": "string",
			"fieldName": "logoLinkUrl",
			"label": "Enter the url you would like to direct users to when they click your logo",
			"tooltip": "Make sure this is a publicly available url and is the full url",
			"placeholder": "e.g. https://www.organization.org/"
		},
		{
			"type": "string",
			"fieldName": "aboutLinkUrl",
			"label": "Enter the url you would like to direct users to when they click About",
			"tooltip": "Make sure this is a publicly available url and is the full url",
			"placeholder": "e.g. https://www.organization.org/"
		},
		{
			"type": "string",
			"fieldName": "downloadLinkUrl",
			"label": "Enter the url you would like to direct users to when they click Download",
			"tooltip": "Make sure this is a publicly available url and is the full url",
			"placeholder": "e.g. http://data.globalforestwatch.org/"
		}]
	},
	{
		"category": "Alternative Language Settings",
		"fields": [{
			"type": "boolean",
			"fieldName": "useAlternativeLanguage",
			"tooltip": "This will allow the application to toggle to an alternative language",
			"label": "Would you like to include an additional language?"
		},
		{
			"type": "options",
			"fieldName": "alternativeLanguage",
			"tooltip": "The alternative language to use in your application",
			"label": "Choose a second language:",
			"options": [{
				"value": "en",
				"label": "English"
			},
			{
				"value": "fr",
				"label": "French"
			},
			{
				"value": "es",
				"label": "Spanish"
			},
			{
				"value": "id",
				"label": "Indonesian"
			},
			{
				"value": "zh",
				"label": "Chinese"
      },
      {
				"value": "ka",
				"label": "Georgian"
      }]
		},
		{
			"type": "string",
			"fieldName": "alternativeWebmap",
			"tooltip": "This should mirror the other webmap configured, but with services in the alternative language",
			"label": "Enter an alternate Web Map Id, this will be activated when the language is changed in the app"
		},
		{
			"type": "string",
			"fieldName": "alternativeLanguageTitle",
			"tooltip": "Same title you configured earlier but in your alternative language",
			"label": "Title for your application in the alternative language",
			"placeholder": "e.g. Forest Atlas of ..."
		},
		{
			"type": "string",
			"fieldName": "alternativeLanguageSubtitle",
			"tooltip": "Same subtitle you configured earlier but in your alternative language",
			"label": "Subtitle for your application in the alternative language",
			"placeholder": "e.g. Ministry of ..."
		},
		{
			"type": "string",
			"fieldName": "alternativeMapThemes",
			"label": "Enter a semi-colon separated list of names for the app ID's(Map Themes) in the alternative language.",
			"tooltip": "Same Map Themes configured above but in your alternative language.",
			"placeholder": "e.g. Forest Atlas of Cameroon;Forest Atlas of Equatorial Guinea"
		},
		{
			"type": "string",
			"fieldName": "alternativeWebmapMenuName",
			"label": "Title for the menu of your webmap",
			"tooltip": "Menu title configured in your alternative language.",
			"placeholder": "Land Use"
		},
		{
			"type": "string",
			"fieldName": "alternativeNarrative",
			"label": "Enter a narrative about your map to give your users some insight about it.",
			"tooltip": "This will be visible in the table of contents.",
			"placeholder": "Explore the Forest Atlas of Cameroon to discover ..."
		}]
	},
	{
		"category": "Analysis Settings",
		"fields": [{
			"type": "boolean",
			"fieldName": "sadAlerts",
			"tooltip": "This will include/exclude this layer from the report, analysis, and layer list",
			"label": "Include SAD alerts (Brazil only) in your application",
			"value": true
		},
		{
			"type": "boolean",
			"fieldName": "gladAlerts",
			"tooltip": "This will include/exclude this layer from the report, analysis, and layer list",
			"label": "Include GLAD alerts (Brazil, Peru, Congo and Borneo only) in your application",
			"value": true
		},
		{
			"type": "boolean",
			"fieldName": "terraIAlerts",
			"tooltip": "This will include/exclude this layer from the report, analysis, and layer list",
			"label": "Include Terra-I alerts (Pan tropics) in your application",
			"value": true
		},
		{
			"type": "boolean",
			"fieldName": "activeFires",
			"tooltip": "This will include/exclude this layer from the report, analysis, and layer list",
			"label": "Include Active Fires in your application",
			"value": true
		},
		{
			"type": "boolean",
			"fieldName": "intactForests",
			"tooltip": "This will include/exclude this layer from the report, analysis, and layer list",
			"label": "Include Intact Forests in your application",
			"value": true
		},
		{
			"type": "boolean",
			"fieldName": "aboveGroundBiomass",
			"tooltip": "This will include/exclude this layer from the report, analysis, and layer list",
			"label": "Include Above Ground Biomass in your application",
			"value": true
		},
		{
			"type": "boolean",
			"fieldName": "landCover",
			"tooltip": "This will include/exclude this layer from the report, analysis, and layer list",
			"label": "Include Land Cover in your application",
			"value": true
		},
		{
			"type": "boolean",
			"fieldName": "mangroves",
			"tooltip": "This will include/exclude this layer from the report, analysis, and layer list",
			"label": "Include Mangroves in your application",
			"value": true
		}]
	},
	{
		"category": "Advanced Settings",
		"fields": [{
			"type": "string",
			"fieldName": "iso",
			"label": "ISO Code for your mask layer",
			"tooltip": "Please enter the 3-digit ISO code of your country atlas",
			"placeholder": "e.g. CMR or COD"
		},
		{
			"type": "string",
			"fieldName": "mapThemeIds",
			"label": "Enter a semi-colon separated list of web app ID's(Map Themes) for other Forest Atlas applications.",
			"tooltip": "These will be linked to from within your application under the Map Themes header.",
			"placeholder": "e.g. 1c38ba1095fe49e3ba234bf9105c1077;c76d788b7487476bae4d09a4e933be19"
		},
		{
			"type": "string",
			"fieldName": "mapThemes",
			"label": "Enter a semi-colon separated list of names for the app ID's configured above(Map Themes).",
			"tooltip": "These will be visible when you hover over map themes and take you to the app added above.",
			"placeholder": "e.g. Forest Atlas of Cameroon;Forest Atlas of Equatorial Guinea"
		},
		{
			"type": "boolean",
			"fieldName": "includeDocumentsTab",
			"tooltip": "Attachments of feature layers will be shown in a separate tab",
			"label": "Show attached documents in separate tab",
			"value": true
		}]
	}],
	"values": {

	}
}
